cxx/__init__.py
cxx/api/__init__.py
cxx/api/builder/__init__.py
cxx/api/builder/class_builder.py
cxx/api/builder/compound_statement_builder.py
cxx/api/builder/document_builder.py
cxx/api/builder/enum_builder.py
cxx/api/builder/function_builder.py
cxx/api/builder/function_call_operator_builder.py
cxx/api/builder/namespace_builder.py
cxx/api/builder/variable_declaration_builder.py
cxx/api/factory/__init__.py
cxx/api/factory/declarations.py
cxx/api/factory/documents.py
cxx/api/factory/literals.py
cxx/api/factory/operators.py
cxx/api/factory/statements.py
cxx/declaration/__init__.py
cxx/declaration/class_declaration/__init__.py
cxx/declaration/class_declaration/class_access.py
cxx/declaration/class_declaration/class_base.py
cxx/declaration/class_declaration/class_declaration.py
cxx/declaration/class_declaration/class_declaration_block.py
cxx/declaration/class_declaration/class_definition.py
cxx/declaration/declaration.py
cxx/declaration/enum_declaration/__init__.py
cxx/declaration/enum_declaration/enum_declaration.py
cxx/declaration/enum_declaration/enum_definition.py
cxx/declaration/enum_declaration/enum_member.py
cxx/declaration/function_declaration/__init__.py
cxx/declaration/function_declaration/constructor_initializer.py
cxx/declaration/function_declaration/function_argument.py
cxx/declaration/function_declaration/function_declaration.py
cxx/declaration/function_declaration/function_definition.py
cxx/declaration/namespace_declaration/__init__.py
cxx/declaration/namespace_declaration/namespace_declaration.py
cxx/declaration/namespace_declaration/namespace_definition.py
cxx/declaration/simple_declaration/__init__.py
cxx/declaration/simple_declaration/alias_declaration.py
cxx/declaration/simple_declaration/simple_declaration.py
cxx/declaration/simple_declaration/static_assert_declaration.py
cxx/declaration/simple_declaration/using_declaration.py
cxx/declaration/simple_declaration/variable_declaration.py
cxx/document/__init__.py
cxx/document/document.py
cxx-0.3.0.dist-info/METADATA
cxx-0.3.0.dist-info/WHEEL
cxx-0.3.0.dist-info/RECORD
