Metadata-Version: 2.1
Name: cxx
Version: 0.3.0
Summary: A C/C++ source generation package.
Author: Omer Lubin
Author-email: omer.lubin.1337@gmail.com
Requires-Python: >=3.11,<4.0
Classifier: Programming Language :: Python :: 3
Classifier: Programming Language :: Python :: 3.11
Project-URL: download, https://pypi.org/project/cxx/#files
Project-URL: source, https://github.com/omer54463/cxx
Project-URL: tracker, https://github.com/omer54463/cxx/issues
